CHANGELOG.md
LICENSE
MANIFEST.in
Makefile
README.md
setup.py
pyne2001/__init__.py
pyne2001/_version.py
pyne2001/core.py
pyne2001.egg-info/PKG-INFO
pyne2001.egg-info/SOURCES.txt
pyne2001.egg-info/dependency_links.txt
pyne2001.egg-info/top_level.txt
pyne2001/NE2001/bin/fort.24
pyne2001/NE2001/bin/fort.25
pyne2001/NE2001/bin/fort.99
pyne2001/NE2001/bin/gal01.inp
pyne2001/NE2001/bin/log_arms.out
pyne2001/NE2001/bin/ne_arms_log_mod.inp
pyne2001/NE2001/bin/ne_gc.inp
pyne2001/NE2001/bin/neclumpN.NE2001.dat
pyne2001/NE2001/bin/nelism.inp
pyne2001/NE2001/bin/nevoidN.NE2001.dat
pyne2001/NE2001/src/Makefile
pyne2001/NE2001/src/NE2001.f
pyne2001/NE2001/src/density.NE2001.f
pyne2001/NE2001/src/dmdsm.NE2001.f
pyne2001/NE2001/src/fort.24
pyne2001/NE2001/src/fort.25
pyne2001/NE2001/src/neLISM.NE2001.f
pyne2001/NE2001/src/neclumpN.NE2001.f
pyne2001/NE2001/src/neclumpN.f
pyne2001/NE2001/src/nevoidN.NE2001.f
pyne2001/NE2001/src/nevoidN.f
pyne2001/NE2001/src/scattering98.f
pyne2001/tests/__init__.py
pyne2001/tests/run_tests.py
pyne2001/tests/test_pyne2001.py