Metadata-Version: 2.1
Name: pyne2001
Version: 0.1.3
Summary: A simple python wrapper around the original FORTRAN implementation of the NE2001 Galactic free electron density model
Home-page: https://github.com/v-morello/pyne2001
Author: Vincent Morello
Author-email: vmorello@gmail.com
License: MIT License
Platform: UNKNOWN
Classifier: Programming Language :: Python :: 2.7
Classifier: Programming Language :: Python :: 3.4
Classifier: Programming Language :: Python :: 3.5
Classifier: Programming Language :: Python :: 3.6
Classifier: Programming Language :: Python :: 3.7
Classifier: Programming Language :: Fortran
Classifier: License :: OSI Approved :: MIT License
Classifier: Operating System :: Unix
Classifier: Topic :: Scientific/Engineering :: Astronomy
